{
  "ticker": "AMAT",
  "info": {
    "symbol": "AMAT",
    "name": "Applied Materials, Inc.",
    "sector": "Technology",
    "industry": "Semiconductor Equipment & Materials",
    "currency": "USD",
    "exchange": "NMS",
    "country": "United States"
  },
  "last_close_date": "2025-06-13",
  "total_records": 11406,
  "first_date": "1980-03-17",
  "last_updated": "2025-06-14T09:33:51.285613",
  "files": {
    "adjusted": "resources\\data\\daily\\AMAT.csv",
    "not_adjusted": "resources\\data\\daily_notAdjusted\\AMAT_notAdjusted.csv"
  }
}