{
  "ticker": "DE",
  "info": {
    "symbol": "DE",
    "name": "Deere & Company",
    "sector": "Industrials",
    "industry": "Agricultural & Farm Machinery",
    "currency": "USD",
    "exchange": "N/A",
    "country": "N/A",
    "source": "CSV"
  },
  "last_close_date": null,
  "first_date": null,
  "total_records": 0,
  "last_updated": "2025-06-13T08:59:32.755552",
  "csv_import": {
    "imported_at": "2025-06-13T08:59:32.755552",
    "company": "Deere & Company",
    "sector": "Industrials",
    "industry": "Agricultural & Farm Machinery"
  },
  "files": {
    "adjusted": "resources\\data\\daily\\DE.csv",
    "not_adjusted": "resources\\data\\daily_notAdjusted\\DE_notAdjusted.csv"
  }
}