{
  "ticker": "INVH",
  "info": {
    "symbol": "INVH",
    "name": "Invitation Homes",
    "sector": "Real Estate",
    "industry": "Single-Family Residential REITs",
    "currency": "USD",
    "exchange": "N/A",
    "country": "N/A",
    "source": "CSV"
  },
  "last_close_date": null,
  "first_date": null,
  "total_records": 0,
  "last_updated": "2025-06-13T08:59:32.977828",
  "csv_import": {
    "imported_at": "2025-06-13T08:59:32.977828",
    "company": "Invitation Homes",
    "sector": "Real Estate",
    "industry": "Single-Family Residential REITs"
  },
  "files": {
    "adjusted": "resources\\data\\daily\\INVH.csv",
    "not_adjusted": "resources\\data\\daily_notAdjusted\\INVH_notAdjusted.csv"
  }
}