{
  "ticker": "KLAC",
  "info": {
    "symbol": "KLAC",
    "name": "KLA Corporation",
    "sector": "Technology",
    "industry": "Semiconductor Equipment & Materials",
    "currency": "USD",
    "exchange": "NMS",
    "country": "United States"
  },
  "last_close_date": "2025-06-13",
  "total_records": 11262,
  "first_date": "1980-10-08",
  "last_updated": "2025-06-14T09:34:47.206486",
  "files": {
    "adjusted": "resources\\data\\daily\\KLAC.csv",
    "not_adjusted": "resources\\data\\daily_notAdjusted\\KLAC_notAdjusted.csv"
  }
}